Metadata-Version: 1.0
Name: tscache
Version: 1.0
Summary: Time Series Data Cache
Home-page: https://github.com/bodhion/tscache
Author: bodhion
Author-email: tscache@bodhion.com
License: MIT
Platform: UNKNOWN
